checkedframe/__init__.py
checkedframe/_checks.py
checkedframe/_config.py
checkedframe/_core.py
checkedframe/_dtypes.py
checkedframe/_narwhals_reexport.py
checkedframe/_schema_generation.py
checkedframe/_utils.py
checkedframe/exceptions.py
checkedframe/modin.py
checkedframe/mypy.py
checkedframe/narwhals.py
checkedframe/pandas.py
checkedframe/polars.py
checkedframe/py.typed
checkedframe/pyarrow.py
checkedframe/selectors.py
checkedframe-0.1.0.dist-info/licenses/LICENSE
checkedframe-0.1.0.dist-info/METADATA
checkedframe-0.1.0.dist-info/WHEEL
checkedframe-0.1.0.dist-info/top_level.txt
checkedframe-0.1.0.dist-info/RECORD
