Metadata-Version: 2.4
Name: checkedframe
Version: 0.1.0
Summary: A generic dataframe validation library
Author-email: Cangyuan Li <everest229@gmail.com>
Classifier: Programming Language :: Python :: 3
Classifier: License :: OSI Approved :: MIT License
Requires-Python: >=3.9
License-File: LICENSE
Requires-Dist: narwhals>=1.0.0
Provides-Extra: pyperclip
Requires-Dist: pyperclip>=1.0.0; extra == "pyperclip"
Dynamic: license-file
